MANIFEST.in
README.md
setup.py
SpiderKeeper/__init__.py
SpiderKeeper/config.py
SpiderKeeper/run.py
SpiderKeeper/uwsgi.py
SpiderKeeper.egg-info/PKG-INFO
SpiderKeeper.egg-info/SOURCES.txt
SpiderKeeper.egg-info/dependency_links.txt
SpiderKeeper.egg-info/entry_points.txt
SpiderKeeper.egg-info/requires.txt
SpiderKeeper.egg-info/top_level.txt
SpiderKeeper/app/__init__.py
SpiderKeeper/app/proxy/__init__.py
SpiderKeeper/app/proxy/spiderctrl.py
SpiderKeeper/app/proxy/contrib/__init__.py
SpiderKeeper/app/proxy/contrib/scrapy.py
SpiderKeeper/app/schedulers/__init__.py
SpiderKeeper/app/schedulers/common.py
SpiderKeeper/app/spider/__init__.py
SpiderKeeper/app/spider/controller.py
SpiderKeeper/app/spider/model.py
SpiderKeeper/app/static/css/AdminLTE.min.css
SpiderKeeper/app/static/css/app.css
SpiderKeeper/app/static/css/bootstrap.min.css
SpiderKeeper/app/static/css/bootstrap.min.css.map
SpiderKeeper/app/static/css/font-awesome.min.css
SpiderKeeper/app/static/css/ionicons.min.css
SpiderKeeper/app/static/css/alt/AdminLTE-without-plugins.min.css
SpiderKeeper/app/static/css/skins/_all-skins.min.css
SpiderKeeper/app/static/css/skins/skin-black-light.min.css
SpiderKeeper/app/static/fonts/FontAwesome.otf
SpiderKeeper/app/static/fonts/fontawesome-webfont.eot
SpiderKeeper/app/static/fonts/fontawesome-webfont.svg
SpiderKeeper/app/static/fonts/fontawesome-webfont.ttf
SpiderKeeper/app/static/fonts/fontawesome-webfont.woff
SpiderKeeper/app/static/fonts/fontawesome-webfont.woff2
SpiderKeeper/app/static/fonts/glyphicons-halflings-regular.eot
SpiderKeeper/app/static/fonts/glyphicons-halflings-regular.svg
SpiderKeeper/app/static/fonts/glyphicons-halflings-regular.ttf
SpiderKeeper/app/static/fonts/glyphicons-halflings-regular.woff
SpiderKeeper/app/static/fonts/glyphicons-halflings-regular.woff2
SpiderKeeper/app/static/fonts/ionicons.eot
SpiderKeeper/app/static/fonts/ionicons.svg
SpiderKeeper/app/static/fonts/ionicons.ttf
SpiderKeeper/app/static/fonts/ionicons.woff
SpiderKeeper/app/static/js/AdminLTE.min.js
SpiderKeeper/app/static/js/Chart.min.js
SpiderKeeper/app/static/js/bootstrap.min.js
SpiderKeeper/app/static/js/demo.js
SpiderKeeper/app/static/js/fastclick.min.js
SpiderKeeper/app/static/js/html5shiv.min.js
