Metadata-Version: 1.1
Name: SpiderKeeper
Version: 1.2.0
Summary: Admin ui for spider service
Home-page: https://github.com/DormyMo/SpiderKeeper/
Author: Dormy Mo
Author-email: modongming91@gmail.com
License: MIT
Platform: UNKNOWN
Classifier: Development Status :: 4 - Beta
Classifier: License :: OSI Approved :: MIT License
Classifier: Operating System :: OS Independent
Classifier: Programming Language :: Python :: 2.7
Classifier: Programming Language :: Python :: 3.5
